README.md
setup.py
overwatcher/TelegramBot.py
overwatcher/__init__.py
overwatcher/__main__.py
overwatcher/utils.py
overwatcher.egg-info/PKG-INFO
overwatcher.egg-info/SOURCES.txt
overwatcher.egg-info/dependency_links.txt
overwatcher.egg-info/requires.txt
overwatcher.egg-info/top_level.txt