Metadata-Version: 2.1
Name: overwatcher
Version: 0.8
Summary: A simple app for sending telegram notification on completion of a long-running command.
Home-page: https://github.com/zeionara/overwatcher
Author: zeionara
Author-email: zeionara@gmail.com
License: UNKNOWN
Platform: UNKNOWN
Classifier: Programming Language :: Python :: 3
Classifier: License :: OSI Approved :: MIT License
Classifier: Operating System :: OS Independent
